passsc/PassSC.py
passsc/__init__.py
PassSC-0.0.1.dist-info/METADATA
PassSC-0.0.1.dist-info/WHEEL
PassSC-0.0.1.dist-info/entry_points.txt
PassSC-0.0.1.dist-info/top_level.txt
PassSC-0.0.1.dist-info/RECORD
